[
  {
    "uid": 5248204262,
    "password": "SSTAR_BYSTARGMR_ZGkrLgo9",
    "account_id": "16101838600",
    "name": "STAR-ERA⁸⁴⁸⁵",
    "region": "BD",
    "date_created": "2026-06-20 10:39:02",
    "thread_id": 5
  },
  {
    "uid": 5248139328,
    "password": "SSTAR_BYSTARGMR_ReTuNdc0",
    "account_id": "16101777378",
    "name": "STAR-ERA⁸⁸⁰⁸",
    "region": "IND",
    "date_created": "2026-06-20 10:33:11",
    "thread_id": 1
  },
  {
    "uid": 5248126957,
    "password": "SSTAR_BYSTARGMR_R8JRM311",
    "account_id": "16101765503",
    "name": "STAR-ERA⁴³⁷²",
    "region": "ME",
    "date_created": "2026-06-20 10:32:03",
    "thread_id": 3
  },
  {
    "uid": 5248226824,
    "password": "SSTAR_BYSTARGMR_gqDjoIEa",
    "account_id": "16101860195",
    "name": "STAR-ERA⁴³¹⁸",
    "region": "TW",
    "date_created": "2026-06-20 10:41:03",
    "thread_id": 1
  }
]